dataclasses_configobj/__init__.py
dataclasses_configobj/core.py
dataclasses_configobj/util.py
dataclasses_configobj-0.0.4.dist-info/LICENSE
dataclasses_configobj-0.0.4.dist-info/METADATA
dataclasses_configobj-0.0.4.dist-info/WHEEL
dataclasses_configobj-0.0.4.dist-info/top_level.txt
dataclasses_configobj-0.0.4.dist-info/RECORD
