Metadata-Version: 2.1
Name: dataclasses-configobj
Version: 0.0.4
Summary: Easily deserialize Data Classes from ini files
Home-page: https://github.com/JEFuller/dataclasses-configobj
Author: Dave Tapley
Author-email: dave@jefuller.com
License: MIT
Platform: UNKNOWN
Classifier: License :: OSI Approved :: MIT License
Classifier: Programming Language :: Python
Classifier: Programming Language :: Python :: 2
Classifier: Programming Language :: Python :: 3
License-File: LICENSE
Requires-Dist: configobj
Requires-Dist: typing-inspect
